pini/__init__.py
pini/cli.py
pini/config.py
pini/setup/django.py
pini/setup/django_rest_framework.py
pini/setup/fastapi.py
pini/setup/nextjs.py
pini/setup/python_base.py
pini/setup/python_package.py
pini/setup/react_vite.py
pini/templates/LICENSE
pini/templates/README.md.tmpl
pini/templates/frameworks/fastapi/config.py
pini/templates/frameworks/fastapi/gunicorn_conf.py
pini/templates/frameworks/fastapi/app/dependencies.py
pini/templates/frameworks/fastapi/app/main.py
pini/templates/frameworks/fastapi/app/utils/authentication.py
pini/templates/github/gitignore/nextjs
pini/templates/github/gitignore/python
pini/templates/github/gitignore/vite
pini/templates/github/issues/bug_report.yaml
pini/templates/github/issues/feature_request.yaml
pini/templates/github/issues/task.yaml
pini/templates/github/workflows/python_package_release.yaml
pini/templates/pre-commit/js.yaml
pini/templates/pre-commit/python.yaml
pini/templates/prettier/prettierignore
pini/templates/prettier/prettierrc
pini/templates/pyproject/commitizen.toml
pini/templates/pyproject/formatters.toml
pini/templates/pyproject/package.toml
pini-1.5.2.dist-info/METADATA
pini-1.5.2.dist-info/WHEEL
pini-1.5.2.dist-info/entry_points.txt
pini-1.5.2.dist-info/top_level.txt
pini-1.5.2.dist-info/RECORD
