Metadata-Version: 2.4
Name: pini
Version: 1.5.2
Summary: An opinionated Python project initializer that sets up a new project with sensible defaults.
License-Expression: MIT
Classifier: Programming Language :: Python :: 3
Classifier: Operating System :: OS Independent
Requires-Python: >=3.12
Requires-Dist: rich>=14.0.0
Requires-Dist: toml>=0.10.2
Requires-Dist: typer>=0.16.0
